{"adus": [{"id": "adu-1", "type": "Claim", "text": "I like to tell my students that in the middle of the sun there are no problems; that problems only appear where there are human beings thinking.", "quote": null, "isImplicit": false, "positions": [{"start": 6589, "end": 6733}], "metadata": {}, "major": true}, {"id": "adu-2", "type": "Claim", "text": "and an attack on human flourishing.", "quote": null, "isImplicit": false, "positions": [{"start": 20201, "end": 20236}], "metadata": {}}], "statistics": {"total_adus": 2, "adu_types": {"ADUType.CLAIM": 2}}}